sabledocs/__init__.py
sabledocs/__main__.py
sabledocs/comments_parser.py
sabledocs/lunr_search.py
sabledocs/proto_descriptor_parser.py
sabledocs/proto_model.py
sabledocs/sable_config.py
sabledocs/templates/_default/base.html
sabledocs/templates/_default/enum.html
sabledocs/templates/_default/index.html
sabledocs/templates/_default/message.html
sabledocs/templates/_default/package.html
sabledocs/templates/_default/search.html
sabledocs/templates/_default/service.html
sabledocs/templates/_default/type_name.html
sabledocs/templates/_default/static/fontawesome.js
sabledocs/templates/_default/static/lunr.js
sabledocs/templates/_default/static/mystyles.css
sabledocs/templates/_default/static/theme.js
sabledocs-0.18.1025.dist-info/licenses/LICENSE
sabledocs-0.18.1025.dist-info/METADATA
sabledocs-0.18.1025.dist-info/WHEEL
sabledocs-0.18.1025.dist-info/entry_points.txt
sabledocs-0.18.1025.dist-info/top_level.txt
sabledocs-0.18.1025.dist-info/RECORD
