Metadata-Version: 2.4
Name: sabledocs
Version: 0.18.1025
Summary: Static documentation generator for Protobuf and gRPC
Author-email: Mark Vincze <mrk.vincze@gmail.com>
Project-URL: Homepage, https://github.com/markvincze/sabledocs
Project-URL: Bug Tracker, https://github.com/markvincze/sabledocs/issues
Classifier: Programming Language :: Python :: 3.11
Classifier: License :: OSI Approved :: MIT License
Classifier: Operating System :: OS Independent
Requires-Python: >=3.11.0
License-File: LICENSE
Requires-Dist: Jinja2<4.0,>=3.0
Requires-Dist: Markdown<4.0,>=3.0
Requires-Dist: protobuf<7.0,>=4.0
Requires-Dist: lunr<1.0,>=0.6
Requires-Dist: furl<3.0,>=2.0
Dynamic: license-file
